<annotation>
	<folder>train</folder>
	<filename>drone_173.jpg</filename>
	<path>C:\Users\Suyeon Jin\Anaconda3\envs\labelimg\imageset\Object-Detection\train\drone_173.jpg</path>
	<source>
		<database>Unknown</database>
	</source>
	<size>
		<width>500</width>
		<height>500</height>
		<depth>3</depth>
	</size>
	<segmented>0</segmented>
	<object>
		<name>drone</name>
		<pose>Unspecified</pose>
		<truncated>0</truncated>
		<difficult>0</difficult>
		<bndbox>
			<xmin>42</xmin>
			<ymin>120</ymin>
			<xmax>463</xmax>
			<ymax>385</ymax>
		</bndbox>
	</object>
</annotation>
